sluyspy/__init__.py
sluyspy/air_visual.py
sluyspy/cli.py
sluyspy/earth.py
sluyspy/env.py
sluyspy/ephem.py
sluyspy/fit.py
sluyspy/gws.py
sluyspy/html.py
sluyspy/ml.py
sluyspy/numerics.py
sluyspy/pandas.py
sluyspy/plot.py
sluyspy/solar_energy.py
sluyspy/solar_panels.py
sluyspy/system.py
sluyspy/text.py
sluyspy/weather.py
sluyspy/wp_data.py
sluyspy-0.0.45.dist-info/licenses/LICENCE
sluyspy-0.0.45.dist-info/METADATA
sluyspy-0.0.45.dist-info/WHEEL
sluyspy-0.0.45.dist-info/top_level.txt
sluyspy-0.0.45.dist-info/RECORD
