Metadata-Version: 2.4
Name: sluyspy
Version: 0.0.45
Summary: Marc van der Sluys' personal Python modules.
Author-email: Marc van der Sluys <git@vandersluys.nl>
License-Expression: EUPL-1.2
Project-URL: GitHub, https://github.com/MarcvdSluys/sluyspy
Project-URL: ReadTheDocs, https://sluyspy.readthedocs.io
Keywords: personal,private
Classifier: Development Status :: 3 - Alpha
Classifier: Intended Audience :: Developers
Classifier: Intended Audience :: Education
Classifier: Intended Audience :: Science/Research
Classifier: Natural Language :: English
Classifier: Operating System :: OS Independent
Classifier: Programming Language :: Python :: 3
Classifier: Topic :: Scientific/Engineering
Classifier: Topic :: Scientific/Engineering :: Astronomy
Classifier: Topic :: Scientific/Engineering :: Physics
License-File: LICENCE
Requires-Dist: astroconst
Requires-Dist: astroquery
Requires-Dist: astrotool
Requires-Dist: matplotlib
Requires-Dist: numpy
Requires-Dist: pandas
Requires-Dist: pytz
Requires-Dist: scipy
Requires-Dist: solarenergy
Requires-Dist: termcolor
Dynamic: license-file
